MANIFEST.in
README.md
setup.cfg
setup.py
django_smart_xw/__init__.py
django_smart_xw/auto_register.py
django_smart_xw/django_admin_helper.py
django_smart_xw/django_helper.py
django_smart_xw/models.py
django_smart_xw/models_test.py
django_smart_xw.egg-info/PKG-INFO
django_smart_xw.egg-info/SOURCES.txt
django_smart_xw.egg-info/dependency_links.txt
django_smart_xw.egg-info/entry_points.txt
django_smart_xw.egg-info/requires.txt
django_smart_xw.egg-info/top_level.txt
django_smart_xw/tests/__init__.py
django_smart_xw/tests/test_dsa.py